basic_cal_001/__init__.py
basic_cal_001/main.py
basic_cal_001-0.0.1.dist-info/licenses/LICENSE.txt
basic_cal_001-0.0.1.dist-info/METADATA
basic_cal_001-0.0.1.dist-info/WHEEL
basic_cal_001-0.0.1.dist-info/top_level.txt
basic_cal_001-0.0.1.dist-info/RECORD
